altendpyqt5/__init__.py
altendpyqt5/_version.py
altendpyqt5/attrs.py
altendpyqt5/core.py
altendpyqt5/models.py
altendpyqt5/tests/__init__.py
altendpyqt5/tests/test_attrs.py
altendpyqt5/tests/test_core.py
altendpyqt5-0.0.3.dist-info/METADATA
altendpyqt5-0.0.3.dist-info/RECORD
altendpyqt5-0.0.3.dist-info/WHEEL
altendpyqt5-0.0.3.dist-info/top_level.txt
