Metadata-Version: 2.1
Name: altendpyqt5
Version: 0.0.3
Summary: Extras for working with PyQt5.
Home-page: https://github.com/altendky/altendpyqt5
Author: Kyle Altendorf
Author-email: sda@fstab.net
License: UNKNOWN
Platform: UNKNOWN
Classifier: Development Status :: 3 - Alpha
Classifier: Intended Audience :: Developers
Classifier: Programming Language :: Python :: 3
Classifier: Programming Language :: Python :: 3.5
Classifier: Programming Language :: Python :: 3.6
Provides-Extra: test
Provides-Extra: dev
Requires-Dist: altendpy
Requires-Dist: attrs
Requires-Dist: pyqt5
Provides-Extra: dev
Requires-Dist: gitignoreio; extra == 'dev'
Provides-Extra: test
Requires-Dist: codecov; extra == 'test'
Requires-Dist: pytest; extra == 'test'
Requires-Dist: pytest-cov; extra == 'test'
Requires-Dist: pytest-qt; extra == 'test'
Requires-Dist: pytest-xvfb; extra == 'test'
Requires-Dist: tox; extra == 'test'
